[
   {
      "attributes" : [
         {
            "data" : "2018 Holiday Subscription Discount Promotion.",
            "index" : 0,
            "parameters" : [ 0, 0, 0, 0, 0 ],
            "type" : 1
         }
      ],
      "id" : 1088,
      "parameters" : [ 0, 0, 0, 0, 0 ],
      "version" : 95
   },
   {
      "attributes" : [
         {
            "data" : "2018 Holiday Subscription Discount Promotion.",
            "index" : 0,
            "parameters" : [ 0, 0, 0, 0, 0 ],
            "type" : 1
         }
      ],
      "id" : 1089,
      "parameters" : [ 0, 0, 0, 0, 0 ],
      "version" : 14
   },
   {
      "attributes" : [
         {
            "data" : "2018 Holiday Subscription Discount Promotion.",
            "index" : 0,
            "parameters" : [ 0, 0, 0, 0, 0 ],
            "type" : 1
         }
      ],
      "id" : 1090,
      "parameters" : [ 0, 0, 0, 0, 0 ],
      "version" : 9
   },
   {
      "attributes" : [
         {
            "data" : "2018 Holiday Subscription Discount Promotion.",
            "index" : 0,
            "parameters" : [ 0, 0, 0, 0, 0 ],
            "type" : 1
         }
      ],
      "id" : 1091,
      "parameters" : [ 0, 0, 0, 0, 0 ],
      "version" : 6
   },
   {
      "attributes" : [
         {
            "data" : "2018 Holiday Subscription Discount Promotion.",
            "index" : 0,
            "parameters" : [ 0, 0, 0, 0, 0 ],
            "type" : 1
         }
      ],
      "id" : 1092,
      "parameters" : [ 0, 0, 0, 0, 0 ],
      "version" : 5
   },
   {
      "attributes" : [
         {
            "data" : "2018 Holiday Subscription Discount Promotion.",
            "index" : 0,
            "parameters" : [ 0, 0, 0, 0, 0 ],
            "type" : 1
         }
      ],
      "id" : 1093,
      "parameters" : [ 0, 0, 0, 0, 0 ],
      "version" : 4
   },
   {
      "attributes" : [
         {
            "data" : ".",
            "index" : 0,
            "parameters" : [ 0, 0, 0, 0, 0 ],
            "type" : 1
         },
         {
            "data" : "",
            "index" : 1,
            "parameters" : [ 0, 0, 0, 0, 0 ],
            "type" : 4
         },
         {
            "data" : "",
            "index" : 3,
            "parameters" : [ 0, 0, 0, 0, 0 ],
            "type" : 5
         },
         {
            "data" : "",
            "index" : 12,
            "parameters" : [ 0, 0, 0, 0, 0 ],
            "type" : 6
         }
      ],
      "id" : 1095,
      "parameters" : [ 0, 0, 0, 0, 0 ],
      "version" : 7
   },
   {
      "attributes" : [
         {
            "data" : "JINGLE ALL THE WAY INSTANT WINNER",
            "index" : 0,
            "parameters" : [ 0, 0, 0, 0, 0 ],
            "type" : 2
         }
      ],
      "id" : 1096,
      "parameters" : [ 0, 0, 0, 0, 0 ],
      "version" : 5
   },
   {
      "attributes" : [
         {
            "data" : "Please pay the player their $25 cash prize. You have received a $25 credit for validating their coupon. The credit will appear on your daily sales report and the weekly invoice report. SUGGEST THE SALE OF LOTTERY TICKETS.",
            "index" : 0,
            "parameters" : [ 0, 0, 0, 0, 0 ],
            "type" : 3
         }
      ],
      "id" : 1104,
      "parameters" : [ 0, 0, 0, 0, 0 ],
      "version" : 4
   }
]
